ner_data_processor/Corefer.py
ner_data_processor/Ner_Data_Preparation.py
ner_data_processor/__init__.py
ner_data_processor-1.1.1.dist-info/METADATA
ner_data_processor-1.1.1.dist-info/WHEEL
ner_data_processor-1.1.1.dist-info/top_level.txt
ner_data_processor-1.1.1.dist-info/RECORD
