Metadata-Version: 2.4
Name: ner-data-processor
Version: 1.1.1
Summary: A NER Data Preparing Tool
Author-email: boopathiraj <boopathiraj.aideveloper@gmail.com>
License: MIT
Project-URL: Homepage, https://github.com/rajboopathiking/ner-data-processor
Project-URL: Repository, https://github.com/rajboopathiking/ner-data-processor
Classifier: Programming Language :: Python :: 3
Classifier: License :: OSI Approved :: MIT License
Classifier: Operating System :: OS Independent
Requires-Python: >=3.7
Requires-Dist: numpy
Requires-Dist: spacy
Requires-Dist: datasets
Requires-Dist: tqdm
Requires-Dist: pandas
